crowdcurio_client/__init__.py
crowdcurio_client/annotation.py
crowdcurio_client/crowdcurio.py
crowdcurio_client/data.py
crowdcurio_client/event.py
crowdcurio_client/experiment.py
crowdcurio_client/interface.py
crowdcurio_client/project.py
crowdcurio_client/response.py
crowdcurio_client/task.py
crowdcurio_client/user.py
crowdcurio_client-0.2.9.dist-info/LICENSE.txt
crowdcurio_client-0.2.9.dist-info/METADATA
crowdcurio_client-0.2.9.dist-info/WHEEL
crowdcurio_client-0.2.9.dist-info/top_level.txt
crowdcurio_client-0.2.9.dist-info/RECORD
